X_Scraper/X_Image_Scraper.py
X_Scraper/X_Tweet_Scraper.py
X_Scraper/__init__.py
X_Scraper-0.1.2.dist-info/LICENSE
X_Scraper-0.1.2.dist-info/METADATA
X_Scraper-0.1.2.dist-info/WHEEL
X_Scraper-0.1.2.dist-info/top_level.txt
X_Scraper-0.1.2.dist-info/RECORD
