Metadata-Version: 2.1
Name: X-Scraper
Version: 0.1.2
Summary: A Python module to scrape Twitter posts and images
Home-page: https://github.com/Saikat-too/Scraper
Author: Saikat Singha
Author-email: saikatsingha00q@gmail.com
Classifier: Programming Language :: Python :: 3
Classifier: License :: OSI Approved :: MIT License
Classifier: Operating System :: OS Independent
Requires-Python: >=3.6
License-File: LICENSE
Requires-Dist: requests
Requires-Dist: beautifulsoup4
Requires-Dist: selenium
